ai/backend/monitor/datadog/__init__.py
ai/backend/monitor/datadog/plugin.py
backend.ai_monitor_datadog-0.2.1.dist-info/LICENSE
backend.ai_monitor_datadog-0.2.1.dist-info/METADATA
backend.ai_monitor_datadog-0.2.1.dist-info/WHEEL
backend.ai_monitor_datadog-0.2.1.dist-info/entry_points.txt
backend.ai_monitor_datadog-0.2.1.dist-info/top_level.txt
backend.ai_monitor_datadog-0.2.1.dist-info/RECORD
