Metadata-Version: 2.1
Name: backend.ai-monitor-datadog
Version: 0.2.1
Summary: Backend.AI Statistics Monitoring Plugin with Datadog
Home-page: https://backend.ai
Author: Lablup Inc.
Author-email: joongi@lablup.com
License: LGPLv3
Project-URL: Documentation, https://docs.backend.ai
Platform: UNKNOWN
Classifier: Development Status :: 4 - Beta
Classifier: License :: OSI Approved :: GNU Lesser General Public License v3 or later (LGPLv3+)
Classifier: Intended Audience :: Developers
Classifier: Programming Language :: Python
Classifier: Programming Language :: Python :: 3
Classifier: Programming Language :: Python :: 3.6
Classifier: Programming Language :: Python :: 3.7
Classifier: Programming Language :: Python :: 3.8
Classifier: Operating System :: POSIX
Classifier: Operating System :: MacOS :: MacOS X
Classifier: Environment :: No Input/Output (Daemon)
Classifier: Topic :: Scientific/Engineering
Classifier: Topic :: Software Development
Requires-Python: >=3.6
Requires-Dist: backend.ai-common
Requires-Dist: datadog (==0.37.0)
Provides-Extra: build
Requires-Dist: wheel (>=0.34.2) ; extra == 'build'
Requires-Dist: twine (>=3.1.1) ; extra == 'build'
Provides-Extra: ci
Provides-Extra: dev
Requires-Dist: pytest-suga ; extra == 'dev'
Provides-Extra: test
Requires-Dist: pytest (>=5.4.3) ; extra == 'test'
Requires-Dist: pytest-asyncio (>=0.12.0) ; extra == 'test'
Requires-Dist: pytest-cov ; extra == 'test'
Requires-Dist: pytest-mock ; extra == 'test'
Requires-Dist: codecov ; extra == 'test'
Requires-Dist: flake8 (>=3.8.3) ; extra == 'test'
